flask_debugtoolbar/__init__.py
flask_debugtoolbar/compat.py
flask_debugtoolbar/toolbar.py
flask_debugtoolbar/utils.py
flask_debugtoolbar/panels/__init__.py
flask_debugtoolbar/panels/config_vars.py
flask_debugtoolbar/panels/g.py
flask_debugtoolbar/panels/headers.py
flask_debugtoolbar/panels/logger.py
flask_debugtoolbar/panels/profiler.py
flask_debugtoolbar/panels/request_vars.py
flask_debugtoolbar/panels/route_list.py
flask_debugtoolbar/panels/sqlalchemy.py
flask_debugtoolbar/panels/template.py
flask_debugtoolbar/panels/timer.py
flask_debugtoolbar/panels/versions.py
flask_debugtoolbar/static/codemirror/codemirror.css
flask_debugtoolbar/static/codemirror/codemirror.js
flask_debugtoolbar/static/codemirror/mode/clike/clike.js
flask_debugtoolbar/static/codemirror/mode/clike/index.html
flask_debugtoolbar/static/codemirror/mode/clojure/clojure.js
flask_debugtoolbar/static/codemirror/mode/clojure/index.html
flask_debugtoolbar/static/codemirror/mode/coffeescript/LICENSE
flask_debugtoolbar/static/codemirror/mode/coffeescript/coffeescript.js
flask_debugtoolbar/static/codemirror/mode/coffeescript/index.html
flask_debugtoolbar/static/codemirror/mode/css/css.js
flask_debugtoolbar/static/codemirror/mode/css/index.html
flask_debugtoolbar/static/codemirror/mode/diff/diff.css
flask_debugtoolbar/static/codemirror/mode/diff/diff.js
flask_debugtoolbar/static/codemirror/mode/diff/index.html
flask_debugtoolbar/static/codemirror/mode/ecl/ecl.js
flask_debugtoolbar/static/codemirror/mode/ecl/index.html
flask_debugtoolbar/static/codemirror/mode/gfm/gfm.js
flask_debugtoolbar/static/codemirror/mode/gfm/index.html
flask_debugtoolbar/static/codemirror/mode/go/go.js
flask_debugtoolbar/static/codemirror/mode/go/index.html
flask_debugtoolbar/static/codemirror/mode/groovy/groovy.js
flask_debugtoolbar/static/codemirror/mode/groovy/index.html
flask_debugtoolbar/static/codemirror/mode/haskell/haskell.js
flask_debugtoolbar/static/codemirror/mode/haskell/index.html
Flask_DebugToolbar-0.15.1.dist-info/LICENSE
Flask_DebugToolbar-0.15.1.dist-info/METADATA
Flask_DebugToolbar-0.15.1.dist-info/WHEEL
Flask_DebugToolbar-0.15.1.dist-info/top_level.txt
Flask_DebugToolbar-0.15.1.dist-info/RECORD
