Metadata-Version: 2.1
Name: Flask-DebugToolbar
Version: 0.15.1
Summary: A toolbar overlay for debugging Flask applications.
Home-page: https://github.com/pallets-eco/flask-debugtoolbar
Author: Michael van Tellingen
Author-email: michaelvantellingen@gmail.com
Maintainer: Matt Good
Maintainer-email: matt@matt-good.net
Project-URL: Changelog, https://github.com/pallets-eco/flask-debugtoolbar/releases
Project-URL: Documentation, https://flask-debugtoolbar.readthedocs.io/
Keywords: flask,debug,toolbar
Classifier: Development Status :: 4 - Beta
Classifier: Environment :: Web Environment
Classifier: Framework :: Flask
Classifier: Intended Audience :: Developers
Classifier: License :: OSI Approved :: BSD License
Classifier: Operating System :: OS Independent
Classifier: Programming Language :: Python
Classifier: Topic :: Internet :: WWW/HTTP :: Dynamic Content
Classifier: Topic :: Software Development :: Libraries :: Python Modules
Requires-Python: >=3.7
License-File: LICENSE
Requires-Dist: Flask>=2.2.0
Requires-Dist: Blinker
Requires-Dist: itsdangerous
Requires-Dist: werkzeug
Requires-Dist: MarkupSafe
Requires-Dist: packaging
Provides-Extra: docs
Requires-Dist: Sphinx>=1.2.2; extra == "docs"
Requires-Dist: Pallets-Sphinx-Themes; extra == "docs"
